sgp30/__init__.py
pimoroni_sgp30-0.0.2.dist-info/LICENSE.txt
pimoroni_sgp30-0.0.2.dist-info/METADATA
pimoroni_sgp30-0.0.2.dist-info/WHEEL
pimoroni_sgp30-0.0.2.dist-info/top_level.txt
pimoroni_sgp30-0.0.2.dist-info/RECORD
